rust_chess-0.3.0.dist-info/METADATA
rust_chess-0.3.0.dist-info/WHEEL
rust_chess-0.3.0.dist-info/licenses/LICENSE
rust_chess/__init__.py
rust_chess/__init__.pyi
rust_chess/py.typed
rust_chess/rust_chess.cpython-313-x86_64-linux-gnu.so
rust_chess-0.3.0.dist-info/RECORD
