Metadata-Version: 2.4
Name: rust_chess
Version: 0.3.0
Classifier: Programming Language :: Rust
Classifier: Programming Language :: Python
License-File: LICENSE
Summary: A bridge between the Rust chess crate and Python.
Keywords: rust,chess
License-Expression: MIT
Requires-Python: >=3.10
Project-URL: Repository, https://github.com/nemeott/rust-chess
